poste_sdk/__init__.py
poste_sdk/client.py
poste_sdk/models.py
poste_sdk-0.1.12.dist-info/WHEEL
poste_sdk-0.1.12.dist-info/METADATA
poste_sdk-0.1.12.dist-info/RECORD
