Metadata-Version: 2.1
Name: poste-sdk
Version: 0.1.12
Summary: 
Home-page: https://poste-sdk.readthedocs.io/
License: MIT
Keywords: poste.io,email,poste-sdk
Author: lishulong
Author-email: lishulong.never@gmail.com
Requires-Python: >=3.7,<4.0
Classifier: License :: OSI Approved :: MIT License
Classifier: Programming Language :: Python :: 3
Classifier: Programming Language :: Python :: 3.10
Classifier: Programming Language :: Python :: 3.7
Classifier: Programming Language :: Python :: 3.8
Classifier: Programming Language :: Python :: 3.9
Requires-Dist: httpx (>=0.23.0,<0.24.0)
Requires-Dist: pydantic (>=1.9.1,<2.0.0)
Requires-Dist: zmail (>=0.2.8,<0.3.0)
Project-URL: Repository, https://github.com/lishulongVI/poste-sdk
